{
  "data": {
    "name": "Sandy Sierakowski",
    "teams": [
      {
        "leagueId": 2,
        "managerId": 20,
        "name": "D-land Sandsharks",
        "draftOrder": 0,
        "year": 2021,
        "wins": 0,
        "losses": 0,
        "ties": 0,
        "pointsFor": 0.00,
        "pointsAgainst": 0.00,
        "finish": 0,
        "moves": 0,
        "isPlayoffs": false,
        "isConsolation": false,
        "isBottom": false,
        "isBFL": false,
        "manager": null,
        "league": null,
        "players": [],
        "id": 1266
      },
      {
        "leagueId": 2,
        "managerId": 20,
        "name": "D-land Sandsharks",
        "draftOrder": 2,
        "year": 2020,
        "wins": 2,
        "losses": 12,
        "ties": 0,
        "pointsFor": 1199.02,
        "pointsAgainst": 1440.68,
        "finish": 10,
        "moves": 13,
        "isPlayoffs": false,
        "isConsolation": false,
        "isBottom": true,
        "isBFL": true,
        "manager": null,
        "league": null,
        "players": [],
        "id": 1246
      },
      {
        "leagueId": 2,
        "managerId": 20,
        "name": "Tri-State Sandsharks",
        "draftOrder": 10,
        "year": 2018,
        "wins": 3,
        "losses": 11,
        "ties": 0,
        "pointsFor": 1291.20,
        "pointsAgainst": 1452.90,
        "finish": 10,
        "moves": 7,
        "isPlayoffs": false,
        "isConsolation": false,
        "isBottom": true,
        "isBFL": true,
        "manager": null,
        "league": null,
        "players": [],
        "id": 1208
      },
      {
        "leagueId": 2,
        "managerId": 20,
        "name": "Tri-State Sandsharks",
        "draftOrder": 2,
        "year": 2017,
        "wins": 6,
        "losses": 8,
        "ties": 0,
        "pointsFor": 1161.08,
        "pointsAgainst": 1269.78,
        "finish": 7,
        "moves": 5,
        "isPlayoffs": false,
        "isConsolation": true,
        "isBottom": false,
        "isBFL": false,
        "manager": null,
        "league": null,
        "players": [],
        "id": 1188
      },
      {
        "leagueId": 2,
        "managerId": 20,
        "name": "Tri-State Sandsharks",
        "draftOrder": 3,
        "year": 2016,
        "wins": 12,
        "losses": 2,
        "ties": 0,
        "pointsFor": 1685.60,
        "pointsAgainst": 1346.62,
        "finish": 1,
        "moves": 7,
        "isPlayoffs": true,
        "isConsolation": false,
        "isBottom": false,
        "isBFL": false,
        "manager": null,
        "league": null,
        "players": [],
        "id": 1168
      },
      {
        "leagueId": 2,
        "managerId": 20,
        "name": "Tri-State Sandsharks",
        "draftOrder": 1,
        "year": 2015,
        "wins": 7,
        "losses": 7,
        "ties": 0,
        "pointsFor": 1184.38,
        "pointsAgainst": 1276.34,
        "finish": 7,
        "moves": 16,
        "isPlayoffs": false,
        "isConsolation": true,
        "isBottom": false,
        "isBFL": false,
        "manager": null,
        "league": null,
        "players": [],
        "id": 168
      },
      {
        "leagueId": 2,
        "managerId": 20,
        "name": "Tri-State Sandsharks",
        "draftOrder": 4,
        "year": 2014,
        "wins": 8,
        "losses": 6,
        "ties": 0,
        "pointsFor": 1442.94,
        "pointsAgainst": 1344.94,
        "finish": 3,
        "moves": 8,
        "isPlayoffs": true,
        "isConsolation": false,
        "isBottom": false,
        "isBFL": false,
        "manager": null,
        "league": null,
        "players": [],
        "id": 148
      },
      {
        "leagueId": 2,
        "managerId": 20,
        "name": "Tri-State Sandsharks",
        "draftOrder": 8,
        "year": 2013,
        "wins": 7,
        "losses": 7,
        "ties": 0,
        "pointsFor": 1389.14,
        "pointsAgainst": 1447.22,
        "finish": 4,
        "moves": 13,
        "isPlayoffs": true,
        "isConsolation": false,
        "isBottom": false,
        "isBFL": false,
        "manager": null,
        "league": null,
        "players": [],
        "id": 128
      },
      {
        "leagueId": 2,
        "managerId": 20,
        "name": "Tri-State Sandsharks",
        "draftOrder": 8,
        "year": 2012,
        "wins": 4,
        "losses": 10,
        "ties": 0,
        "pointsFor": 1115.08,
        "pointsAgainst": 1334.96,
        "finish": 10,
        "moves": 8,
        "isPlayoffs": false,
        "isConsolation": false,
        "isBottom": true,
        "isBFL": true,
        "manager": null,
        "league": null,
        "players": [],
        "id": 20
      }
    ],
    "id": 20
  },
  "statusCode": "200",
  "message": null,
  "succeeded": true
}